pict/__init__.py
pict/cli.py
pict-1.0.0.dist-info/LICENSE
pict-1.0.0.dist-info/METADATA
pict-1.0.0.dist-info/WHEEL
pict-1.0.0.dist-info/entry_points.txt
pict-1.0.0.dist-info/top_level.txt
pict-1.0.0.dist-info/RECORD
