Metadata-Version: 2.1
Name: pict
Version: 1.0.0
Summary: A CLI tool to generate project folder structures for Golang, TypeScript, Rust, and Python
Home-page: https://github.com/TheAlchemistKE/pict
Author: Kelyn Njeri
Author-email: kelyn.njeri@gmail.com
Classifier: Programming Language :: Python :: 3
Classifier: License :: OSI Approved :: MIT License
Classifier: Operating System :: OS Independent
Requires-Python: >=3.6
License-File: LICENSE
Requires-Dist: colorama
